[{
  "id":1001,
  "name":"幼儿最爱",
  "area":"China",
  "number":1,
  "parent":null
},{
  "id":1002,
  "name":"如何培养孩子的兴趣",
  "area":"China",
  "number":2,
  "parent":null
},{
  "id":1003,
  "name":"如何提高教学质量",
  "area":"China",
  "number":3,
  "parent":null
},{
  "id":1004,
  "name":"英语真的很难吗？",
  "area":"China",
  "number":4,
  "parent":null
},{
  "id":1005,
  "name":"工程管理",
  "area":"China",
  "number":5,
  "parent":null
},{
  "id":1006,
  "name":"旅游去哪儿",
  "area":"China",
  "number":6,
  "parent":null
},{
  "id":1007,
  "name":"舌尖上的美食",
  "area":"China",
  "number":7,
  "parent":null
},{
  "id":1008,
  "name":"聪明宝宝从胎教做起",
  "area":"China",
  "number":8,
  "parent":null
},{
  "id":1009,
  "name":"正确运动的秘诀",
  "area":"China",
  "number":9,
  "parent":null
},{
  "id":1010,
  "name":"品位从健康生活开始",
  "area":"China",
  "number":10,
  "parent":null
}]